experiment/__init__.py
experiment/run_experiment.py
experiment/trainer.py
experiment/util.py
experiment/version.py
interpolating_neural_networks/__init__.py
interpolating_neural_networks/data/__init__.py
interpolating_neural_networks/data/data_loader.py
interpolating_neural_networks/data/dataset.py
interpolating_neural_networks/models/__init__.py
interpolating_neural_networks/models/mlp.py
interpolating_neural_networks/models/util.py
interpolating_neural_networks-0.0.2.dist-info/LICENSE
interpolating_neural_networks-0.0.2.dist-info/METADATA
interpolating_neural_networks-0.0.2.dist-info/WHEEL
interpolating_neural_networks-0.0.2.dist-info/top_level.txt
interpolating_neural_networks-0.0.2.dist-info/RECORD
