Metadata-Version: 2.1
Name: interpolating-neural-networks
Version: 0.0.2
Summary: Interpolating Neural Networks in Asset Pricing Data. Supports Distributed Training in TensorFlow.
Home-page: https://github.com/akashsonowal/interpolating-neural-networks/
Author: Akash Sonowal
Author-email: work.akashsonowal@gmail.com
License: MIT
Keywords: double descent,deep learning,generalization,asset pricing
Classifier: Development Status :: 4 - Beta
Classifier: Intended Audience :: Developers
Classifier: Operating System :: OS Independent
Classifier: Programming Language :: Python :: 3.8
Classifier: Topic :: Scientific/Engineering :: Artificial Intelligence
Requires-Python: >=3.8
License-File: LICENSE
Requires-Dist: tensorflow
Requires-Dist: scikit-learn
Requires-Dist: numpy
Requires-Dist: pandas
Requires-Dist: wandb
Provides-Extra: dev
Requires-Dist: pytest (==7.1.2) ; extra == 'dev'
Requires-Dist: black (==22.3.0) ; extra == 'dev'
Requires-Dist: flake8 (==3.9.2) ; extra == 'dev'
Requires-Dist: isort (==5.10.1) ; extra == 'dev'
Requires-Dist: pre-commit (==2.19.0) ; extra == 'dev'
Provides-Extra: test
Requires-Dist: pytest (==7.1.2) ; extra == 'test'
